LICENSE
th2_box_descriptor_generator/generate_service_descriptions.py
th2_box_descriptor_generator-0.0.1.dev2370769627.dist-info/LICENSE
th2_box_descriptor_generator-0.0.1.dev2370769627.dist-info/WHEEL
th2_box_descriptor_generator-0.0.1.dev2370769627.dist-info/METADATA
th2_box_descriptor_generator-0.0.1.dev2370769627.dist-info/RECORD
